FRETpredict/FRET.py
FRETpredict/R0_calculation.py
FRETpredict/__init__.py
FRETpredict/lennardjones.py
FRETpredict/libraries.py
FRETpredict/rotamer_libraries.py
FRETpredict/utils.py
FRETpredict/lib/A35_C1R.pdb
FRETpredict/lib/A35_C1R_cutoff10.dcd
FRETpredict/lib/A35_C1R_cutoff10_weights.txt
FRETpredict/lib/A35_C1R_cutoff20.dcd
FRETpredict/lib/A35_C1R_cutoff20_weights.txt
FRETpredict/lib/A35_C1R_cutoff30.dcd
FRETpredict/lib/A35_C1R_cutoff30_weights.txt
FRETpredict/lib/A35_L1R.pdb
FRETpredict/lib/A35_L1R_cutoff10.dcd
FRETpredict/lib/A35_L1R_cutoff10_weights.txt
FRETpredict/lib/A35_L1R_cutoff20.dcd
FRETpredict/lib/A35_L1R_cutoff20_weights.txt
FRETpredict/lib/A35_L1R_cutoff30.dcd
FRETpredict/lib/A35_L1R_cutoff30_weights.txt
FRETpredict/lib/A48_B1R.pdb
FRETpredict/lib/A48_B1R_cutoff10.dcd
FRETpredict/lib/A48_B1R_cutoff10_weights.txt
FRETpredict/lib/A48_B1R_cutoff20.dcd
FRETpredict/lib/A48_B1R_cutoff20_weights.txt
FRETpredict/lib/A48_B1R_cutoff30.dcd
FRETpredict/lib/A48_B1R_cutoff30_weights.txt
FRETpredict/lib/A48_C1R.pdb
FRETpredict/lib/A48_C1R_cutoff10.dcd
FRETpredict/lib/A48_C1R_cutoff10_weights.txt
FRETpredict/lib/A48_C1R_cutoff20.dcd
FRETpredict/lib/A48_C1R_cutoff20_weights.txt
FRETpredict/lib/A48_C1R_cutoff30.dcd
FRETpredict/lib/A48_C1R_cutoff30_weights.txt
FRETpredict/lib/A48_L1R.pdb
FRETpredict/lib/A48_L1R_cutoff10.dcd
FRETpredict/lib/A48_L1R_cutoff10_weights.txt
FRETpredict/lib/A48_L1R_cutoff20.dcd
FRETpredict/lib/A48_L1R_cutoff20_weights.txt
FRETpredict/lib/A48_L1R_cutoff30.dcd
FRETpredict/lib/A48_L1R_cutoff30_weights.txt
FRETpredict/lib/A53_C1R.pdb
FRETpredict/lib/A53_C1R_cutoff10.dcd
FRETpredict/lib/A53_C1R_cutoff10_weights.txt
FRETpredict/lib/A53_C1R_cutoff20.dcd
FRETpredict/lib/A53_C1R_cutoff20_weights.txt
FRETpredict/lib/A53_C1R_cutoff30.dcd
FRETpredict/lib/A53_C1R_cutoff30_weights.txt
FRETpredict/lib/A53_L1R.pdb
FRETpredict/lib/A53_L1R_cutoff10.dcd
FRETpredict/lib/A53_L1R_cutoff10_weights.txt
FRETpredict/lib/A53_L1R_cutoff20.dcd
FRETpredict-0.2.8.dist-info/LICENSE
FRETpredict-0.2.8.dist-info/METADATA
FRETpredict-0.2.8.dist-info/WHEEL
FRETpredict-0.2.8.dist-info/top_level.txt
FRETpredict-0.2.8.dist-info/RECORD
